{
"meta":{"test_sets":[],"test_metrics":[],"learn_metrics":[{"best_value":"Min","name":"RMSE"}],"launch_mode":"Train","parameters":"","iteration_count":400,"learn_sets":["learn"],"name":"experiment"},
"iterations":[
{"learn":[1.008996376],"iteration":0,"passed_time":0.004396519095,"remaining_time":1.754211119},
{"learn":[0.9893268122],"iteration":1,"passed_time":0.01172838021,"remaining_time":2.333947662},
{"learn":[0.970732412],"iteration":2,"passed_time":0.01512828566,"remaining_time":2.001976469},
{"learn":[0.9530115063],"iteration":3,"passed_time":0.01889935484,"remaining_time":1.871036129},
{"learn":[0.9366096742],"iteration":4,"passed_time":0.02630865515,"remaining_time":2.078383756},
{"learn":[0.9217811659],"iteration":5,"passed_time":0.0296707162,"remaining_time":1.948377031},
{"learn":[0.9051067593],"iteration":6,"passed_time":0.03827946718,"remaining_time":2.149118658},
{"learn":[0.8892833291],"iteration":7,"passed_time":0.04267216898,"remaining_time":2.09093628},
{"learn":[0.8764240046],"iteration":8,"passed_time":0.05020813186,"remaining_time":2.181264395},
{"learn":[0.8611103538],"iteration":9,"passed_time":0.05626408569,"remaining_time":2.194299342},
{"learn":[0.8476736687],"iteration":10,"passed_time":0.05936248802,"remaining_time":2.09927344},
{"learn":[0.8341905011],"iteration":11,"passed_time":0.06389792133,"remaining_time":2.06603279},
{"learn":[0.8208475502],"iteration":12,"passed_time":0.07158219985,"remaining_time":2.130947026},
{"learn":[0.8081085971],"iteration":13,"passed_time":0.0796688949,"remaining_time":2.196585245},
{"learn":[0.7961569932],"iteration":14,"passed_time":0.08059085459,"remaining_time":2.068498601},
{"learn":[0.7842377553],"iteration":15,"passed_time":0.08803049984,"remaining_time":2.112731996},
{"learn":[0.7725882083],"iteration":16,"passed_time":0.09695380226,"remaining_time":2.184312133},
{"learn":[0.7612738346],"iteration":17,"passed_time":0.1043752054,"remaining_time":2.215073803},
{"learn":[0.7499243696],"iteration":18,"passed_time":0.1087837437,"remaining_time":2.181400335},
{"learn":[0.7386940333],"iteration":19,"passed_time":0.1136039032,"remaining_time":2.158474162},
{"learn":[0.7295091649],"iteration":20,"passed_time":0.1157992143,"remaining_time":2.089900106},
{"learn":[0.7202142636],"iteration":21,"passed_time":0.1200744599,"remaining_time":2.063097539},
{"learn":[0.7115680612],"iteration":22,"passed_time":0.1308690216,"remaining_time":2.145113962},
{"learn":[0.7014296744],"iteration":23,"passed_time":0.1321779734,"remaining_time":2.070788249},
{"learn":[0.6928323154],"iteration":24,"passed_time":0.1407815324,"remaining_time":2.111722985},
{"learn":[0.6847087582],"iteration":25,"passed_time":0.1427120016,"remaining_time":2.052857254},
{"learn":[0.6764425213],"iteration":26,"passed_time":0.1454838594,"remaining_time":2.009832576},
{"learn":[0.6674069758],"iteration":27,"passed_time":0.1513361931,"remaining_time":2.010609423},
{"learn":[0.6605853141],"iteration":28,"passed_time":0.1548100476,"remaining_time":1.980500954},
{"learn":[0.6543883974],"iteration":29,"passed_time":0.1636621155,"remaining_time":2.018499424},
{"learn":[0.6453753445],"iteration":30,"passed_time":0.1750487381,"remaining_time":2.083644656},
{"learn":[0.6372415131],"iteration":31,"passed_time":0.1799992034,"remaining_time":2.069990839},
{"learn":[0.6307765463],"iteration":32,"passed_time":0.1831470099,"remaining_time":2.036816746},
{"learn":[0.6238391441],"iteration":33,"passed_time":0.1869123443,"remaining_time":2.012056412},
{"learn":[0.6175124585],"iteration":34,"passed_time":0.1910067355,"remaining_time":1.991927384},
{"learn":[0.6114835941],"iteration":35,"passed_time":0.1952304721,"remaining_time":1.973996996},
{"learn":[0.6035702421],"iteration":36,"passed_time":0.201454003,"remaining_time":1.976427111},
{"learn":[0.5955086607],"iteration":37,"passed_time":0.2061364945,"remaining_time":1.963721343},
{"learn":[0.5884403054],"iteration":38,"passed_time":0.2106732943,"remaining_time":1.950078442},
{"learn":[0.5828144666],"iteration":39,"passed_time":0.213896528,"remaining_time":1.925068752},
{"learn":[0.5769935083],"iteration":40,"passed_time":0.2158406006,"remaining_time":1.889921356},
{"learn":[0.5715736099],"iteration":41,"passed_time":0.2203678316,"remaining_time":1.878373422},
{"learn":[0.5659870059],"iteration":42,"passed_time":0.2274696264,"remaining_time":1.888526899},
{"learn":[0.5604759966],"iteration":43,"passed_time":0.2356105465,"remaining_time":1.906303512},
{"learn":[0.5560035787],"iteration":44,"passed_time":0.2441367215,"remaining_time":1.92596747},
{"learn":[0.5500803385],"iteration":45,"passed_time":0.256798565,"remaining_time":1.976232435},
{"learn":[0.5450600653],"iteration":46,"passed_time":0.2593495525,"remaining_time":1.947880681},
{"learn":[0.5409187868],"iteration":47,"passed_time":0.2650247419,"remaining_time":1.943514774},
{"learn":[0.5364071503],"iteration":48,"passed_time":0.2687108017,"remaining_time":1.924846763},
{"learn":[0.5322619712],"iteration":49,"passed_time":0.2724195487,"remaining_time":1.906936841},
{"learn":[0.5281113703],"iteration":50,"passed_time":0.2735243508,"remaining_time":1.871764675},
{"learn":[0.5231501295],"iteration":51,"passed_time":0.2776824725,"remaining_time":1.858336547},
{"learn":[0.5179827303],"iteration":52,"passed_time":0.2800945726,"remaining_time":1.83382673},
{"learn":[0.5138723076],"iteration":53,"passed_time":0.2832677625,"remaining_time":1.81501196},
{"learn":[0.510688132],"iteration":54,"passed_time":0.2857091271,"remaining_time":1.792175433},
{"learn":[0.5070995481],"iteration":55,"passed_time":0.2911203969,"remaining_time":1.788311009},
{"learn":[0.5024374725],"iteration":56,"passed_time":0.2955278044,"remaining_time":1.778351525},
{"learn":[0.498816202],"iteration":57,"passed_time":0.2997419022,"remaining_time":1.76744363},
{"learn":[0.4960725578],"iteration":58,"passed_time":0.3011264805,"remaining_time":1.74040898},
{"learn":[0.4924845612],"iteration":59,"passed_time":0.3079118893,"remaining_time":1.744834039},
{"learn":[0.4881913901],"iteration":60,"passed_time":0.3101828269,"remaining_time":1.723802923},
{"learn":[0.484519901],"iteration":61,"passed_time":0.3115545188,"remaining_time":1.698474635},
{"learn":[0.4814114928],"iteration":62,"passed_time":0.3138676869,"remaining_time":1.678943024},
{"learn":[0.4774794568],"iteration":63,"passed_time":0.3158958768,"remaining_time":1.658453353},
{"learn":[0.4737177388],"iteration":64,"passed_time":0.31675875,"remaining_time":1.632525865},
{"learn":[0.4703236712],"iteration":65,"passed_time":0.3190537264,"remaining_time":1.614605222},
{"learn":[0.4662102343],"iteration":66,"passed_time":0.3221349239,"remaining_time":1.601058652},
{"learn":[0.4627020428],"iteration":67,"passed_time":0.3247725166,"remaining_time":1.585654052},
{"learn":[0.4575741252],"iteration":68,"passed_time":0.3282996441,"remaining_time":1.574886699},
{"learn":[0.4551880474],"iteration":69,"passed_time":0.3303108299,"remaining_time":1.557179626},
{"learn":[0.4524457401],"iteration":70,"passed_time":0.3328415156,"remaining_time":1.542321953},
{"learn":[0.4491944257],"iteration":71,"passed_time":0.3350043866,"remaining_time":1.526131095},
{"learn":[0.4459583629],"iteration":72,"passed_time":0.3381136437,"remaining_time":1.514563856},
{"learn":[0.4438899875],"iteration":73,"passed_time":0.3405331126,"remaining_time":1.500186415},
{"learn":[0.4402741824],"iteration":74,"passed_time":0.3444263157,"remaining_time":1.492514035},
{"learn":[0.4375384205],"iteration":75,"passed_time":0.3465773946,"remaining_time":1.477514156},
{"learn":[0.434998811],"iteration":76,"passed_time":0.3474287913,"remaining_time":1.457396098},
{"learn":[0.4329134978],"iteration":77,"passed_time":0.3497895597,"remaining_time":1.444003054},
{"learn":[0.429767823],"iteration":78,"passed_time":0.352803602,"remaining_time":1.43354375},
{"learn":[0.4277929377],"iteration":79,"passed_time":0.3561220055,"remaining_time":1.424488022},
{"learn":[0.423937319],"iteration":80,"passed_time":0.3578829933,"remaining_time":1.409440431},
{"learn":[0.4202197236],"iteration":81,"passed_time":0.3598789658,"remaining_time":1.395628184},
{"learn":[0.4166063424],"iteration":82,"passed_time":0.363784621,"remaining_time":1.389394275},
{"learn":[0.4145498245],"iteration":83,"passed_time":0.3656580485,"remaining_time":1.375570754},
{"learn":[0.4121316573],"iteration":84,"passed_time":0.3708353311,"remaining_time":1.37427211},
{"learn":[0.4100758574],"iteration":85,"passed_time":0.3731002229,"remaining_time":1.362249651},
{"learn":[0.4080998315],"iteration":86,"passed_time":0.3755332379,"remaining_time":1.351056362},
{"learn":[0.4064050401],"iteration":87,"passed_time":0.3777874903,"remaining_time":1.339428375},
{"learn":[0.404223746],"iteration":88,"passed_time":0.3793928887,"remaining_time":1.32574369},
{"learn":[0.4024074395],"iteration":89,"passed_time":0.3822913091,"remaining_time":1.316781176},
{"learn":[0.4002621035],"iteration":90,"passed_time":0.3845144144,"remaining_time":1.305658836},
{"learn":[0.3970396516],"iteration":91,"passed_time":0.3872521584,"remaining_time":1.296452878},
{"learn":[0.3957247188],"iteration":92,"passed_time":0.3890399029,"remaining_time":1.284250002},
{"learn":[0.3938147313],"iteration":93,"passed_time":0.3920475923,"remaining_time":1.276240035},
{"learn":[0.3906202381],"iteration":94,"passed_time":0.3969614112,"remaining_time":1.274455057},
{"learn":[0.3880671588],"iteration":95,"passed_time":0.4018935725,"remaining_time":1.272662979},
{"learn":[0.3856387453],"iteration":96,"passed_time":0.4050188368,"remaining_time":1.265161934},
{"learn":[0.3829804405],"iteration":97,"passed_time":0.4087348707,"remaining_time":1.259570724},
{"learn":[0.3815243191],"iteration":98,"passed_time":0.4127935008,"remaining_time":1.255059028},
{"learn":[0.3785403537],"iteration":99,"passed_time":0.4169253871,"remaining_time":1.250776161},
{"learn":[0.3771901708],"iteration":100,"passed_time":0.4188587464,"remaining_time":1.239987774},
{"learn":[0.3753233216],"iteration":101,"passed_time":0.4206867791,"remaining_time":1.229065296},
{"learn":[0.3725155227],"iteration":102,"passed_time":0.4265436281,"remaining_time":1.229936481},
{"learn":[0.3711704124],"iteration":103,"passed_time":0.4282433845,"remaining_time":1.218846556},
{"learn":[0.3695547146],"iteration":104,"passed_time":0.430658879,"remaining_time":1.209946374},
{"learn":[0.3682535301],"iteration":105,"passed_time":0.4332373403,"remaining_time":1.201620548},
{"learn":[0.366872389],"iteration":106,"passed_time":0.4347882778,"remaining_time":1.190588462},
{"learn":[0.3652623101],"iteration":107,"passed_time":0.4386794362,"remaining_time":1.186059216},
{"learn":[0.3637255128],"iteration":108,"passed_time":0.4407523946,"remaining_time":1.176687586},
{"learn":[0.362441562],"iteration":109,"passed_time":0.4429566916,"remaining_time":1.167794914},
{"learn":[0.3608154242],"iteration":110,"passed_time":0.4442156297,"remaining_time":1.156561414},
{"learn":[0.359652132],"iteration":111,"passed_time":0.445517572,"remaining_time":1.145616614},
{"learn":[0.3568251681],"iteration":112,"passed_time":0.447348306,"remaining_time":1.136185521},
{"learn":[0.355141934],"iteration":113,"passed_time":0.4496928066,"remaining_time":1.12817669},
{"learn":[0.353788261],"iteration":114,"passed_time":0.4508810413,"remaining_time":1.117400842},
{"learn":[0.3528981701],"iteration":115,"passed_time":0.4520965992,"remaining_time":1.106857191},
{"learn":[0.3511916848],"iteration":116,"passed_time":0.453408174,"remaining_time":1.096705241},
{"learn":[0.3505523183],"iteration":117,"passed_time":0.4546283726,"remaining_time":1.086484755},
{"learn":[0.3491455357],"iteration":118,"passed_time":0.4584190489,"remaining_time":1.082485317},
{"learn":[0.3480434952],"iteration":119,"passed_time":0.4602016515,"remaining_time":1.073803854},
{"learn":[0.3469231017],"iteration":120,"passed_time":0.4615510686,"remaining_time":1.064237588},
{"learn":[0.3457663005],"iteration":121,"passed_time":0.4635653634,"remaining_time":1.056321074},
{"learn":[0.3449738355],"iteration":122,"passed_time":0.4656022819,"remaining_time":1.04855148},
{"learn":[0.3421312414],"iteration":123,"passed_time":0.4679766365,"remaining_time":1.041625417},
{"learn":[0.3399044917],"iteration":124,"passed_time":0.4713997538,"remaining_time":1.037079458},
{"learn":[0.3386688451],"iteration":125,"passed_time":0.4742551797,"remaining_time":1.031316819},
{"learn":[0.3377029088],"iteration":126,"passed_time":0.4775403583,"remaining_time":1.026523762},
{"learn":[0.3358572719],"iteration":127,"passed_time":0.4796098487,"remaining_time":1.019170929},
{"learn":[0.3338940999],"iteration":128,"passed_time":0.4811854383,"remaining_time":1.010862432},
{"learn":[0.3330147823],"iteration":129,"passed_time":0.4841628608,"remaining_time":1.005569019},
{"learn":[0.3322420471],"iteration":130,"passed_time":0.4855076372,"remaining_time":0.9969584306},
{"learn":[0.3314960199],"iteration":131,"passed_time":0.4871069467,"remaining_time":0.9889747099},
{"learn":[0.3306291748],"iteration":132,"passed_time":0.4896288971,"remaining_time":0.9829392145},
{"learn":[0.3297287834],"iteration":133,"passed_time":0.4916579794,"remaining_time":0.9759777799},
{"learn":[0.3286017642],"iteration":134,"passed_time":0.4929924419,"remaining_time":0.9677259045},
{"learn":[0.3267182343],"iteration":135,"passed_time":0.494920205,"remaining_time":0.9607274567},
{"learn":[0.3250797469],"iteration":136,"passed_time":0.4970218296,"remaining_time":0.954136797},
{"learn":[0.3242955273],"iteration":137,"passed_time":0.4993280016,"remaining_time":0.9479995393},
{"learn":[0.3234060861],"iteration":138,"passed_time":0.5007473554,"remaining_time":0.9402522285},
{"learn":[0.3215542956],"iteration":139,"passed_time":0.5025841483,"remaining_time":0.9333705612},
{"learn":[0.3205232008],"iteration":140,"passed_time":0.5042806019,"remaining_time":0.9263026659},
{"learn":[0.3188298541],"iteration":141,"passed_time":0.5056556534,"remaining_time":0.9187264688},
{"learn":[0.318030528],"iteration":142,"passed_time":0.5069468359,"remaining_time":0.9110862716},
{"learn":[0.3171927977],"iteration":143,"passed_time":0.5082794491,"remaining_time":0.9036079095},
{"learn":[0.3156576472],"iteration":144,"passed_time":0.5107390959,"remaining_time":0.8981963411},
{"learn":[0.3144567011],"iteration":145,"passed_time":0.5121595319,"remaining_time":0.8910172678},
{"learn":[0.3137496854],"iteration":146,"passed_time":0.5127645294,"remaining_time":0.8825131016},
{"learn":[0.3132367168],"iteration":147,"passed_time":0.5142289072,"remaining_time":0.8755789501},
{"learn":[0.3122397433],"iteration":148,"passed_time":0.5156925682,"remaining_time":0.8687170108},
{"learn":[0.3114424529],"iteration":149,"passed_time":0.5168466841,"remaining_time":0.8614111402},
{"learn":[0.3101976409],"iteration":150,"passed_time":0.5183411311,"remaining_time":0.8547479579},
{"learn":[0.3095698962],"iteration":151,"passed_time":0.5197041748,"remaining_time":0.8479383905},
{"learn":[0.3078992246],"iteration":152,"passed_time":0.5214584371,"remaining_time":0.8418315945},
{"learn":[0.3065728665],"iteration":153,"passed_time":0.5238830427,"remaining_time":0.8368521331},
{"learn":[0.3059750971],"iteration":154,"passed_time":0.5256452733,"remaining_time":0.8308586579},
{"learn":[0.3044457284],"iteration":155,"passed_time":0.5272448234,"remaining_time":0.8246649802},
{"learn":[0.3036680526],"iteration":156,"passed_time":0.5297978256,"remaining_time":0.8200055517},
{"learn":[0.3027620355],"iteration":157,"passed_time":0.5325416938,"remaining_time":0.8156651259},
{"learn":[0.3016903439],"iteration":158,"passed_time":0.5334526833,"remaining_time":0.8085666457},
{"learn":[0.3008355017],"iteration":159,"passed_time":0.5362331709,"remaining_time":0.8043497564},
{"learn":[0.2999950384],"iteration":160,"passed_time":0.5398493493,"remaining_time":0.80139127},
{"learn":[0.2992910159],"iteration":161,"passed_time":0.5413722921,"remaining_time":0.7953494167},
{"learn":[0.2985209369],"iteration":162,"passed_time":0.5433759604,"remaining_time":0.7900619793},
{"learn":[0.2978574795],"iteration":163,"passed_time":0.5450466396,"remaining_time":0.7843354082},
{"learn":[0.2973656349],"iteration":164,"passed_time":0.5461120206,"remaining_time":0.7777959081},
{"learn":[0.2966401982],"iteration":165,"passed_time":0.5474818297,"remaining_time":0.7717514948},
{"learn":[0.295893698],"iteration":166,"passed_time":0.5513854168,"remaining_time":0.7692982162},
{"learn":[0.2952536947],"iteration":167,"passed_time":0.5525098842,"remaining_time":0.7629898401},
{"learn":[0.2946092911],"iteration":168,"passed_time":0.554004186,"remaining_time":0.7572483253},
{"learn":[0.2932993551],"iteration":169,"passed_time":0.5564038342,"remaining_time":0.7527816581},
{"learn":[0.2923067493],"iteration":170,"passed_time":0.5583494033,"remaining_time":0.7477310722},
{"learn":[0.2912817552],"iteration":171,"passed_time":0.5601272953,"remaining_time":0.7424943216},
{"learn":[0.2903693509],"iteration":172,"passed_time":0.5610276751,"remaining_time":0.7361461402},
{"learn":[0.2894218319],"iteration":173,"passed_time":0.5619220359,"remaining_time":0.7298527593},
{"learn":[0.2884693073],"iteration":174,"passed_time":0.5657252563,"remaining_time":0.7273610438},
{"learn":[0.2877542807],"iteration":175,"passed_time":0.5704876721,"remaining_time":0.7260752191},
{"learn":[0.2873054075],"iteration":176,"passed_time":0.5726777162,"remaining_time":0.721509213},
{"learn":[0.2866846519],"iteration":177,"passed_time":0.5742332795,"remaining_time":0.7161785845},
{"learn":[0.286066266],"iteration":178,"passed_time":0.5750013437,"remaining_time":0.70991786},
{"learn":[0.2854036319],"iteration":179,"passed_time":0.5767500932,"remaining_time":0.7049167806},
{"learn":[0.2850115078],"iteration":180,"passed_time":0.5787205749,"remaining_time":0.7002199221},
{"learn":[0.2842404423],"iteration":181,"passed_time":0.5799057426,"remaining_time":0.694612373},
{"learn":[0.2834620786],"iteration":182,"passed_time":0.5818301026,"remaining_time":0.6899296845},
{"learn":[0.2830700578],"iteration":183,"passed_time":0.5840358997,"remaining_time":0.6856073606},
{"learn":[0.2824836517],"iteration":184,"passed_time":0.5856233767,"remaining_time":0.6805893297},
{"learn":[0.2818493871],"iteration":185,"passed_time":0.5880486189,"remaining_time":0.6765720669},
{"learn":[0.2813739426],"iteration":186,"passed_time":0.5920962336,"remaining_time":0.6744197741},
{"learn":[0.2806572873],"iteration":187,"passed_time":0.5937774022,"remaining_time":0.6695787727},
{"learn":[0.2801352849],"iteration":188,"passed_time":0.5960570429,"remaining_time":0.6654393442},
{"learn":[0.2795116398],"iteration":189,"passed_time":0.5995274494,"remaining_time":0.6626356019},
{"learn":[0.2791354393],"iteration":190,"passed_time":0.6038025966,"remaining_time":0.6607054591},
{"learn":[0.2785414067],"iteration":191,"passed_time":0.6059637822,"remaining_time":0.656460764},
{"learn":[0.2780892821],"iteration":192,"passed_time":0.6069727127,"remaining_time":0.6510018214},
{"learn":[0.2776095633],"iteration":193,"passed_time":0.6079517391,"remaining_time":0.6455570013},
{"learn":[0.2767263124],"iteration":194,"passed_time":0.6088437848,"remaining_time":0.640066543},
{"learn":[0.2757572848],"iteration":195,"passed_time":0.6116660341,"remaining_time":0.6366319947},
{"learn":[0.2751594146],"iteration":196,"passed_time":0.6130413677,"remaining_time":0.6317126784},
{"learn":[0.2743398127],"iteration":197,"passed_time":0.6148012913,"remaining_time":0.6272215194},
{"learn":[0.2737900358],"iteration":198,"passed_time":0.6158477285,"remaining_time":0.6220371529},
{"learn":[0.2734739864],"iteration":199,"passed_time":0.6183804441,"remaining_time":0.6183804441},
{"learn":[0.2730364408],"iteration":200,"passed_time":0.6194436901,"remaining_time":0.6132800713},
{"learn":[0.2725343475],"iteration":201,"passed_time":0.6207144923,"remaining_time":0.6084231162},
{"learn":[0.2719466945],"iteration":202,"passed_time":0.6220030169,"remaining_time":0.6036186913},
{"learn":[0.271085908],"iteration":203,"passed_time":0.6243339163,"remaining_time":0.5998502334},
{"learn":[0.2701793994],"iteration":204,"passed_time":0.6250772835,"remaining_time":0.5945857087},
{"learn":[0.2693611741],"iteration":205,"passed_time":0.6269351952,"remaining_time":0.5904146984},
{"learn":[0.2688608378],"iteration":206,"passed_time":0.6281172858,"remaining_time":0.5856359234},
{"learn":[0.268479465],"iteration":207,"passed_time":0.6297155777,"remaining_time":0.5812759179},
{"learn":[0.2681001927],"iteration":208,"passed_time":0.633945136,"remaining_time":0.5793469903},
{"learn":[0.2675562571],"iteration":209,"passed_time":0.638990681,"remaining_time":0.5781344257},
{"learn":[0.2671423166],"iteration":210,"passed_time":0.640380256,"remaining_time":0.5736107506},
{"learn":[0.2666298243],"iteration":211,"passed_time":0.6438797898,"remaining_time":0.5709877381},
{"learn":[0.2659969516],"iteration":212,"passed_time":0.6464217382,"remaining_time":0.5675157983},
{"learn":[0.2655679752],"iteration":213,"passed_time":0.6491876674,"remaining_time":0.5642472249},
{"learn":[0.2650332586],"iteration":214,"passed_time":0.6507690102,"remaining_time":0.5599640321},
{"learn":[0.2642440295],"iteration":215,"passed_time":0.6528897071,"remaining_time":0.5561653061},
{"learn":[0.2638747779],"iteration":216,"passed_time":0.6537422215,"remaining_time":0.5513125647},
{"learn":[0.2635186739],"iteration":217,"passed_time":0.6564810229,"remaining_time":0.5480713127},
{"learn":[0.2631207246],"iteration":218,"passed_time":0.6579769484,"remaining_time":0.5438074323},
{"learn":[0.2624721051],"iteration":219,"passed_time":0.6603191236,"remaining_time":0.5402611011},
{"learn":[0.2620676514],"iteration":220,"passed_time":0.662160833,"remaining_time":0.5363203127},
{"learn":[0.2613648429],"iteration":221,"passed_time":0.6649046611,"remaining_time":0.5331217553},
{"learn":[0.2606752988],"iteration":222,"passed_time":0.666868404,"remaining_time":0.5293081054},
{"learn":[0.2601884228],"iteration":223,"passed_time":0.6681354289,"remaining_time":0.5249635513},
{"learn":[0.259907526],"iteration":224,"passed_time":0.6702975986,"remaining_time":0.5213425767},
{"learn":[0.2595187203],"iteration":225,"passed_time":0.6712973528,"remaining_time":0.5168395548},
{"learn":[0.2590134233],"iteration":226,"passed_time":0.672415626,"remaining_time":0.5124577238},
{"learn":[0.2584655366],"iteration":227,"passed_time":0.6732767703,"remaining_time":0.507910546},
{"learn":[0.2581631253],"iteration":228,"passed_time":0.6744352463,"remaining_time":0.5036175857},
{"learn":[0.2575023315],"iteration":229,"passed_time":0.6758932692,"remaining_time":0.4995732859},
{"learn":[0.2571232895],"iteration":230,"passed_time":0.6766942044,"remaining_time":0.4950706517},
{"learn":[0.2568439485],"iteration":231,"passed_time":0.6779024755,"remaining_time":0.490894896},
{"learn":[0.2565213034],"iteration":232,"passed_time":0.678598373,"remaining_time":0.4863773746},
{"learn":[0.2563160434],"iteration":233,"passed_time":0.6793332454,"remaining_time":0.4819201655},
{"learn":[0.2561007857],"iteration":234,"passed_time":0.6802951424,"remaining_time":0.4776540362},
{"learn":[0.2554373939],"iteration":235,"passed_time":0.6810712452,"remaining_time":0.4732867975},
{"learn":[0.2548528276],"iteration":236,"passed_time":0.6827534611,"remaining_time":0.4695730555},
{"learn":[0.2544446152],"iteration":237,"passed_time":0.684493365,"remaining_time":0.4659156518},
{"learn":[0.2542352923],"iteration":238,"passed_time":0.6855208685,"remaining_time":0.4617943926},
{"learn":[0.2535481325],"iteration":239,"passed_time":0.6865258099,"remaining_time":0.4576838732},
{"learn":[0.2527305973],"iteration":240,"passed_time":0.6872351584,"remaining_time":0.4534041087},
{"learn":[0.2523291699],"iteration":241,"passed_time":0.6880949144,"remaining_time":0.4492520516},
{"learn":[0.2517830507],"iteration":242,"passed_time":0.6898814831,"remaining_time":0.4457258965},
{"learn":[0.2511256409],"iteration":243,"passed_time":0.6909582887,"remaining_time":0.4417602174},
{"learn":[0.2508253563],"iteration":244,"passed_time":0.6919669538,"remaining_time":0.4377750116},
{"learn":[0.250277823],"iteration":245,"passed_time":0.6930009824,"remaining_time":0.4338298833},
{"learn":[0.2500488876],"iteration":246,"passed_time":0.6938144414,"remaining_time":0.4297716985},
{"learn":[0.2496819017],"iteration":247,"passed_time":0.6947599956,"remaining_time":0.4258206425},
{"learn":[0.2493366356],"iteration":248,"passed_time":0.6959383342,"remaining_time":0.4220348934},
{"learn":[0.2486189632],"iteration":249,"passed_time":0.6970617927,"remaining_time":0.4182370756},
{"learn":[0.2481426119],"iteration":250,"passed_time":0.6981554389,"remaining_time":0.4144428701},
{"learn":[0.2478232192],"iteration":251,"passed_time":0.6992285125,"remaining_time":0.4106580153},
{"learn":[0.2474725638],"iteration":252,"passed_time":0.6998604723,"remaining_time":0.4066382982},
{"learn":[0.2469567879],"iteration":253,"passed_time":0.7006816544,"remaining_time":0.4027540218},
{"learn":[0.2466783409],"iteration":254,"passed_time":0.7018311196,"remaining_time":0.3990804405},
{"learn":[0.2461709662],"iteration":255,"passed_time":0.7031339992,"remaining_time":0.3955128745},
{"learn":[0.2457951314],"iteration":256,"passed_time":0.7040963871,"remaining_time":0.3917734761},
{"learn":[0.2454892983],"iteration":257,"passed_time":0.7053795764,"remaining_time":0.3882321699},
{"learn":[0.2449841838],"iteration":258,"passed_time":0.7063800022,"remaining_time":0.3845543641},
{"learn":[0.2447205309],"iteration":259,"passed_time":0.7071762466,"remaining_time":0.3807872097},
{"learn":[0.2443763872],"iteration":260,"passed_time":0.708325812,"remaining_time":0.377230988},
{"learn":[0.244025156],"iteration":261,"passed_time":0.7096798698,"remaining_time":0.3738008475},
{"learn":[0.2435274974],"iteration":262,"passed_time":0.7104844031,"remaining_time":0.3701002404},
{"learn":[0.2433037835],"iteration":263,"passed_time":0.7112109967,"remaining_time":0.3663814225},
{"learn":[0.2429206202],"iteration":264,"passed_time":0.7125858325,"remaining_time":0.3630154241},
{"learn":[0.2423765879],"iteration":265,"passed_time":0.713435856,"remaining_time":0.3594000177},
{"learn":[0.2419769608],"iteration":266,"passed_time":0.7141369737,"remaining_time":0.3557311517},
{"learn":[0.2417176283],"iteration":267,"passed_time":0.715179542,"remaining_time":0.3522526103},
{"learn":[0.241257315],"iteration":268,"passed_time":0.7162219499,"remaining_time":0.348792102},
{"learn":[0.2410234895],"iteration":269,"passed_time":0.7170184049,"remaining_time":0.3452310838},
{"learn":[0.2405325008],"iteration":270,"passed_time":0.7180083966,"remaining_time":0.3417825947},
{"learn":[0.240207991],"iteration":271,"passed_time":0.7186975536,"remaining_time":0.3382106135},
{"learn":[0.2398069083],"iteration":272,"passed_time":0.7194304766,"remaining_time":0.3346801118},
{"learn":[0.2395656485],"iteration":273,"passed_time":0.7203215349,"remaining_time":0.3312427496},
{"learn":[0.2393342765],"iteration":274,"passed_time":0.7215476472,"remaining_time":0.3279762033},
{"learn":[0.2391436406],"iteration":275,"passed_time":0.7233436808,"remaining_time":0.3249804943},
{"learn":[0.2387698831],"iteration":276,"passed_time":0.7243152551,"remaining_time":0.3216273515},
{"learn":[0.2383902791],"iteration":277,"passed_time":0.725378386,"remaining_time":0.3183315219},
{"learn":[0.2381889031],"iteration":278,"passed_time":0.726237681,"remaining_time":0.3149632953},
{"learn":[0.2379631024],"iteration":279,"passed_time":0.7275787035,"remaining_time":0.3118194444},
{"learn":[0.2376775973],"iteration":280,"passed_time":0.7289403489,"remaining_time":0.3086971584},
{"learn":[0.2373882383],"iteration":281,"passed_time":0.7301682352,"remaining_time":0.3055313892},
{"learn":[0.2369386197],"iteration":282,"passed_time":0.7309813936,"remaining_time":0.3022078553},
{"learn":[0.2366901701],"iteration":283,"passed_time":0.7320038806,"remaining_time":0.2989875005},
{"learn":[0.2362888699],"iteration":284,"passed_time":0.7328861936,"remaining_time":0.2957260079},
{"learn":[0.2360378284],"iteration":285,"passed_time":0.7336420046,"remaining_time":0.2924307291},
{"learn":[0.2356183916],"iteration":286,"passed_time":0.7350631574,"remaining_time":0.2894151108},
{"learn":[0.2354487692],"iteration":287,"passed_time":0.7356818867,"remaining_time":0.2860985115},
{"learn":[0.2351968766],"iteration":288,"passed_time":0.7366955029,"remaining_time":0.282952252},
{"learn":[0.2349495759],"iteration":289,"passed_time":0.7375179679,"remaining_time":0.2797481947},
{"learn":[0.2345969407],"iteration":290,"passed_time":0.7386445202,"remaining_time":0.2766744079},
{"learn":[0.2343405713],"iteration":291,"passed_time":0.7394002207,"remaining_time":0.273476794},
{"learn":[0.2341701674],"iteration":292,"passed_time":0.7401151273,"remaining_time":0.2702809509},
{"learn":[0.2340905929],"iteration":293,"passed_time":0.7421416083,"remaining_time":0.2675748656},
{"learn":[0.2337593068],"iteration":294,"passed_time":0.7434729136,"remaining_time":0.2646259523},
{"learn":[0.2335369435],"iteration":295,"passed_time":0.7442407406,"remaining_time":0.2614899899},
{"learn":[0.2333369348],"iteration":296,"passed_time":0.7452562363,"remaining_time":0.2584558665},
{"learn":[0.232983736],"iteration":297,"passed_time":0.7460929391,"remaining_time":0.2553740932},
{"learn":[0.2327738248],"iteration":298,"passed_time":0.7474302482,"remaining_time":0.2524764384},
{"learn":[0.2323833474],"iteration":299,"passed_time":0.7487611024,"remaining_time":0.2495870341},
{"learn":[0.2321529685],"iteration":300,"passed_time":0.7495589955,"remaining_time":0.2465326929},
{"learn":[0.2319978464],"iteration":301,"passed_time":0.7502573636,"remaining_time":0.2434609988},
{"learn":[0.2314718957],"iteration":302,"passed_time":0.7511291622,"remaining_time":0.2404604909},
{"learn":[0.2311817272],"iteration":303,"passed_time":0.7522404043,"remaining_time":0.2375496014},
{"learn":[0.2309551124],"iteration":304,"passed_time":0.7529835108,"remaining_time":0.2345358476},
{"learn":[0.2306875403],"iteration":305,"passed_time":0.7542771992,"remaining_time":0.2317060677},
{"learn":[0.2304878043],"iteration":306,"passed_time":0.7552215956,"remaining_time":0.2287804833},
{"learn":[0.2301935878],"iteration":307,"passed_time":0.7561959514,"remaining_time":0.2258767128},
{"learn":[0.2299358703],"iteration":308,"passed_time":0.757255604,"remaining_time":0.2230105501},
{"learn":[0.2294605655],"iteration":309,"passed_time":0.7582421982,"remaining_time":0.2201348317},
{"learn":[0.2292243419],"iteration":310,"passed_time":0.758961264,"remaining_time":0.2171947026},
{"learn":[0.2291086477],"iteration":311,"passed_time":0.7598496714,"remaining_time":0.214316574},
{"learn":[0.2288597527],"iteration":312,"passed_time":0.7635435607,"remaining_time":0.2122309578},
{"learn":[0.2286942049],"iteration":313,"passed_time":0.7643366327,"remaining_time":0.2093406064},
{"learn":[0.2284416857],"iteration":314,"passed_time":0.7656292285,"remaining_time":0.2065983633},
{"learn":[0.2280850868],"iteration":315,"passed_time":0.7682291825,"remaining_time":0.2042128207},
{"learn":[0.2278799044],"iteration":316,"passed_time":0.7692588729,"remaining_time":0.2014147837},
{"learn":[0.2276129245],"iteration":317,"passed_time":0.7703698892,"remaining_time":0.1986488394},
{"learn":[0.2273428209],"iteration":318,"passed_time":0.771187015,"remaining_time":0.1958186464},
{"learn":[0.227273907],"iteration":319,"passed_time":0.7719676133,"remaining_time":0.1929919033},
{"learn":[0.227045468],"iteration":320,"passed_time":0.7732132406,"remaining_time":0.1902923552},
{"learn":[0.2267744881],"iteration":321,"passed_time":0.7744811944,"remaining_time":0.1876072458},
{"learn":[0.2265490925],"iteration":322,"passed_time":0.7763092623,"remaining_time":0.1850644371},
{"learn":[0.2262013856],"iteration":323,"passed_time":0.7773202825,"remaining_time":0.1823343873},
{"learn":[0.2259923243],"iteration":324,"passed_time":0.7785674534,"remaining_time":0.1796694123},
{"learn":[0.225661147],"iteration":325,"passed_time":0.7808451749,"remaining_time":0.1772470642},
{"learn":[0.2253047546],"iteration":326,"passed_time":0.781892454,"remaining_time":0.1745509148},
{"learn":[0.2250525975],"iteration":327,"passed_time":0.7830410424,"remaining_time":0.1718870581},
{"learn":[0.224838982],"iteration":328,"passed_time":0.7849814695,"remaining_time":0.1694032959},
{"learn":[0.2245198489],"iteration":329,"passed_time":0.7864310781,"remaining_time":0.1668187135},
{"learn":[0.2242461544],"iteration":330,"passed_time":0.7879341152,"remaining_time":0.1642521267},
{"learn":[0.2241262974],"iteration":331,"passed_time":0.7889455363,"remaining_time":0.1615912544},
{"learn":[0.2239908859],"iteration":332,"passed_time":0.790036378,"remaining_time":0.1589562682},
{"learn":[0.2239215156],"iteration":333,"passed_time":0.7908805862,"remaining_time":0.1562817925},
{"learn":[0.2236640231],"iteration":334,"passed_time":0.791560577,"remaining_time":0.1535863806},
{"learn":[0.2235962685],"iteration":335,"passed_time":0.7923100883,"remaining_time":0.1509162073},
{"learn":[0.2233505342],"iteration":336,"passed_time":0.7932520594,"remaining_time":0.1482934117},
{"learn":[0.2230471292],"iteration":337,"passed_time":0.7942893874,"remaining_time":0.1456980533},
{"learn":[0.2228379913],"iteration":338,"passed_time":0.795003589,"remaining_time":0.1430537431},
{"learn":[0.2227715782],"iteration":339,"passed_time":0.7957764825,"remaining_time":0.140431144},
{"learn":[0.2225337849],"iteration":340,"passed_time":0.7965039146,"remaining_time":0.1378115278},
{"learn":[0.2222181807],"iteration":341,"passed_time":0.7971850663,"remaining_time":0.1351951282},
{"learn":[0.2220916188],"iteration":342,"passed_time":0.7979629832,"remaining_time":0.1326060934},
{"learn":[0.2219438903],"iteration":343,"passed_time":0.7999405665,"remaining_time":0.1302228829},
{"learn":[0.2218242303],"iteration":344,"passed_time":0.8009824532,"remaining_time":0.1276928549},
{"learn":[0.2216900309],"iteration":345,"passed_time":0.802026525,"remaining_time":0.1251717698},
{"learn":[0.221504362],"iteration":346,"passed_time":0.80299554,"remaining_time":0.1226477338},
{"learn":[0.2213178828],"iteration":347,"passed_time":0.8037442896,"remaining_time":0.1200997214},
{"learn":[0.2211475222],"iteration":348,"passed_time":0.8044682352,"remaining_time":0.1175583954},
{"learn":[0.2210286201],"iteration":349,"passed_time":0.8052639782,"remaining_time":0.1150377112},
{"learn":[0.2209013195],"iteration":350,"passed_time":0.8062758856,"remaining_time":0.1125570325},
{"learn":[0.2205988936],"iteration":351,"passed_time":0.8072612117,"remaining_time":0.1100810743},
{"learn":[0.2204662816],"iteration":352,"passed_time":0.8079439506,"remaining_time":0.1075732739},
{"learn":[0.2202343151],"iteration":353,"passed_time":0.8086504207,"remaining_time":0.1050788682},
{"learn":[0.2200502932],"iteration":354,"passed_time":0.8093230596,"remaining_time":0.102590247},
{"learn":[0.219843379],"iteration":355,"passed_time":0.8099442646,"remaining_time":0.1001054709},
{"learn":[0.2196031375],"iteration":356,"passed_time":0.8108526496,"remaining_time":0.0976657253},
{"learn":[0.2193715464],"iteration":357,"passed_time":0.8116371417,"remaining_time":0.09521999987},
{"learn":[0.2191898911],"iteration":358,"passed_time":0.8124595396,"remaining_time":0.09278785828},
{"learn":[0.2188927267],"iteration":359,"passed_time":0.8139681645,"remaining_time":0.09044090716},
{"learn":[0.2187826079],"iteration":360,"passed_time":0.81469993,"remaining_time":0.08801467387},
{"learn":[0.2187192018],"iteration":361,"passed_time":0.8153731599,"remaining_time":0.08559165767},
{"learn":[0.2184264643],"iteration":362,"passed_time":0.816051988,"remaining_time":0.08317885277},
{"learn":[0.2181409571],"iteration":363,"passed_time":0.8167136765,"remaining_time":0.08077388009},
{"learn":[0.2180254734],"iteration":364,"passed_time":0.8173619038,"remaining_time":0.07837716886},
{"learn":[0.2179057339],"iteration":365,"passed_time":0.8179751604,"remaining_time":0.07598676354},
{"learn":[0.2176233645],"iteration":366,"passed_time":0.8186050907,"remaining_time":0.07360754222},
{"learn":[0.2174613506],"iteration":367,"passed_time":0.8196995489,"remaining_time":0.07127822164},
{"learn":[0.2173632425],"iteration":368,"passed_time":0.8204399491,"remaining_time":0.06892584939},
{"learn":[0.2173014481],"iteration":369,"passed_time":0.8211561903,"remaining_time":0.06658023165},
{"learn":[0.2171932784],"iteration":370,"passed_time":0.8218358102,"remaining_time":0.06424053503},
{"learn":[0.2170344583],"iteration":371,"passed_time":0.8225070507,"remaining_time":0.06190913285},
{"learn":[0.2169299995],"iteration":372,"passed_time":0.8231342343,"remaining_time":0.05958344324},
{"learn":[0.2166909986],"iteration":373,"passed_time":0.823866987,"remaining_time":0.05727417556},
{"learn":[0.2165929485],"iteration":374,"passed_time":0.8246143233,"remaining_time":0.05497428822},
{"learn":[0.2163245354],"iteration":375,"passed_time":0.8253749403,"remaining_time":0.05268350683},
{"learn":[0.2161335839],"iteration":376,"passed_time":0.8263771204,"remaining_time":0.05041558029},
{"learn":[0.2159356138],"iteration":377,"passed_time":0.8270501952,"remaining_time":0.04813519654},
{"learn":[0.2157747492],"iteration":378,"passed_time":0.8276839792,"remaining_time":0.04586111758},
{"learn":[0.2155081958],"iteration":379,"passed_time":0.8283882861,"remaining_time":0.04359938348},
{"learn":[0.2153537548],"iteration":380,"passed_time":0.8292356884,"remaining_time":0.04135296084},
{"learn":[0.215235642],"iteration":381,"passed_time":0.8299841625,"remaining_time":0.03910920138},
{"learn":[0.215124148],"iteration":382,"passed_time":0.8308677135,"remaining_time":0.03687924577},
{"learn":[0.2149990804],"iteration":383,"passed_time":0.8316261655,"remaining_time":0.03465109023},
{"learn":[0.2149143807],"iteration":384,"passed_time":0.8325435628,"remaining_time":0.03243676219},
{"learn":[0.2147930964],"iteration":385,"passed_time":0.8332074163,"remaining_time":0.0302199581},
{"learn":[0.2146455921],"iteration":386,"passed_time":0.8339864877,"remaining_time":0.02801504997},
{"learn":[0.2145860374],"iteration":387,"passed_time":0.8347273691,"remaining_time":0.02581631038},
{"learn":[0.214438709],"iteration":388,"passed_time":0.8354867733,"remaining_time":0.02362558999},
{"learn":[0.2141715222],"iteration":389,"passed_time":0.8365301784,"remaining_time":0.02144949175},
{"learn":[0.2139160147],"iteration":390,"passed_time":0.8377770938,"remaining_time":0.01928387173},
{"learn":[0.2136716736],"iteration":391,"passed_time":0.8385285597,"remaining_time":0.01711282775},
{"learn":[0.213456522],"iteration":392,"passed_time":0.8395243599,"remaining_time":0.0149533601},
{"learn":[0.2133572929],"iteration":393,"passed_time":0.8404621462,"remaining_time":0.01279891593},
{"learn":[0.213172976],"iteration":394,"passed_time":0.8412484978,"remaining_time":0.01064871516},
{"learn":[0.2129299599],"iteration":395,"passed_time":0.8422368958,"remaining_time":0.008507443392},
{"learn":[0.2127014509],"iteration":396,"passed_time":0.8430073355,"remaining_time":0.00637033251},
{"learn":[0.2125038304],"iteration":397,"passed_time":0.8439278117,"remaining_time":0.004240843275},
{"learn":[0.2122366024],"iteration":398,"passed_time":0.8446520346,"remaining_time":0.002116922393},
{"learn":[0.2121610468],"iteration":399,"passed_time":0.8454106771,"remaining_time":0}
]}